verbia_core/__init__.py
verbia_core/entry.py
verbia_core/error.py
verbia_core/dictionary/__init__.py
verbia_core/dictionary/base.py
verbia_core/dictionary/factory.py
verbia_core/dictionary/word.py
verbia_core/dictionary/gemini/__init__.py
verbia_core/dictionary/gemini/client.py
verbia_core/dictionary/gemini/dictionary.py
verbia_core/utils/__init__.py
verbia_core/utils/id_generator.py
verbia_core/utils/time_provider.py
verbia_core/vocabulary/__init__.py
verbia_core/vocabulary/review.py
verbia_core/vocabulary/storage.py
verbia_core/vocabulary/vocabulary.py
verbia_core-0.1.3.dist-info/METADATA
verbia_core-0.1.3.dist-info/WHEEL
verbia_core-0.1.3.dist-info/RECORD
