Metadata-Version: 2.4
Name: verbia-core
Version: 0.1.3
Requires-Python: >=3.12
Requires-Dist: aiohttp>=3.11.10
Requires-Dist: langcodes>=3.5.0
Requires-Dist: loguru>=0.7.2
Requires-Dist: requests>=2.32.3
